emg-toolbox/__init__.py
emg-toolbox/features.py
emg-toolbox/filters.py
emg-toolbox/plots.py
emg_toolbox/__init__.py
emg_toolbox/features.py
emg_toolbox/filters.py
emg_toolbox/plots.py
emg_toolbox-1.1.0.dist-info/METADATA
emg_toolbox-1.1.0.dist-info/WHEEL
emg_toolbox-1.1.0.dist-info/top_level.txt
emg_toolbox-1.1.0.dist-info/RECORD
