Metadata-Version: 2.1
Name: emg_toolbox
Version: 1.1.0
Summary: EMG Toolbox is a Python toolkit for processing and analysing surface electromyography (sEMG) data. It includes a variety of feature extraction methods, signal filtering, and plotting functions, helping users efficiently preprocess and analyse EMG signals.
Home-page: https://github.com/your_username/your_repository
Author: Linus Zhang
Author-email: products@wearlab.tech
Classifier: Development Status :: 3 - Alpha
Classifier: Intended Audience :: Developers
Classifier: License :: OSI Approved :: MIT License
Classifier: Programming Language :: Python :: 3
Classifier: Programming Language :: Python :: 3.6
Classifier: Programming Language :: Python :: 3.7
Classifier: Programming Language :: Python :: 3.8
Classifier: Programming Language :: Python :: 3.9
Classifier: Programming Language :: Python :: 3.10
Classifier: Programming Language :: Python :: 3.11
Requires-Python: >=3.6
Requires-Dist: pandas
Requires-Dist: seaborn
Requires-Dist: matplotlib
Requires-Dist: numpy
Requires-Dist: scipy
